apifipecons/__init__.py
apifipecons-0.0.1.dist-info/LICENSE
apifipecons-0.0.1.dist-info/METADATA
apifipecons-0.0.1.dist-info/WHEEL
apifipecons-0.0.1.dist-info/top_level.txt
apifipecons-0.0.1.dist-info/RECORD
