Metadata-Version: 2.1
Name: apifipecons
Version: 0.0.1
Summary: "Metodos para aconsumo de API da FIPE"
Home-page: https://github.com/rpsjr/apifipecons
Author: "RAIMUNDO PEREIRA DA SILVA JUNIOR"
Author-email: "raimundopsjr@gmail.com"
License: UNKNOWN
Project-URL: Bug Tracker, https://github.com/rpsjr/apifipecons/issues
Platform: UNKNOWN
Classifier: Programming Language :: Python :: 3
Classifier: License :: OSI Approved :: MIT License
Classifier: Operating System :: OS Independent
Requires-Python: >=3.6
